parrotflume/__init__.py
parrotflume/__main__.py
parrotflume/auto_completer.py
parrotflume/config.py
parrotflume/fallbacks.py
parrotflume/fancy.py
parrotflume/model_quirks.py
parrotflume/tools.py
parrotflume-0.0.12.dist-info/METADATA
parrotflume-0.0.12.dist-info/WHEEL
parrotflume-0.0.12.dist-info/entry_points.txt
parrotflume-0.0.12.dist-info/licenses/LICENSE
parrotflume-0.0.12.dist-info/RECORD
