Metadata-Version: 2.4
Name: parrotflume
Version: 0.0.12
Summary: parrotflume: Process data from a pipe or file with an OpenAI-compatible API, or chat with it on a CLI.
Project-URL: Homepage, https://github.com/iehgit/parrotflume
Project-URL: Repository, https://github.com/iehgit/parrotflume
Project-URL: Issues, https://github.com/iehgit/parrotflume/issues
Author-email: Sebastian Dalfuß <py@sedf.de>
License: Extended MIT License
License-File: LICENSE
Classifier: Development Status :: 4 - Beta
Classifier: Environment :: Console
Classifier: Intended Audience :: Developers
Classifier: Intended Audience :: Science/Research
Classifier: License :: OSI Approved :: MIT License
Classifier: Operating System :: OS Independent
Classifier: Programming Language :: Python :: 3.12
Classifier: Programming Language :: Python :: 3.13
Classifier: Topic :: Text Processing :: General
Classifier: Topic :: Utilities
Requires-Python: >=3.12
Requires-Dist: appdirs>=1.4.4
Requires-Dist: openai>=1.59.6
Requires-Dist: pylatexenc>=2.10
Requires-Dist: sympy>=1.12.1
